spinqkit/__init__.py
spinqkit/spinq_backends.cp39-win_amd64.pyd
spinqkit/algorithm/__init__.py
spinqkit/algorithm/hhl.py
spinqkit/algorithm/qaoa.py
spinqkit/algorithm/quantum_counting.py
spinqkit/algorithm/random_circuit.py
spinqkit/algorithm/shor.py
spinqkit/algorithm/vqe.py
spinqkit/algorithm/optimizer/__init__.py
spinqkit/algorithm/optimizer/adam.py
spinqkit/algorithm/optimizer/optimizer.py
spinqkit/algorithm/optimizer/utils.py
spinqkit/backend/__init__.py
spinqkit/backend/backend.py
spinqkit/backend/backend_util.py
spinqkit/backend/basic_simulator_backend.py
spinqkit/backend/spinq_cloud_backend.py
spinqkit/backend/triangulum_backend.py
spinqkit/backend/client/__init__.py
spinqkit/backend/client/spinq_cloud_client.py
spinqkit/backend/client/spinq_session.py
spinqkit/backend/layout/__init__.py
spinqkit/backend/layout/layout.py
spinqkit/backend/layout/layout_util.py
spinqkit/backend/layout/physical_layout.py
spinqkit/backend/layout/routing_layout.py
spinqkit/backend/layout/sven_swap_mapper.py
spinqkit/compiler/__init__.py
spinqkit/compiler/compiler.py
spinqkit/compiler/ir.py
spinqkit/compiler/native_compiler.py
spinqkit/compiler/qasm_compiler.py
spinqkit/compiler/qiskit_compiler.py
spinqkit/compiler/decomposer/ZYZdecomposer.py
spinqkit/compiler/decomposer/__init__.py
spinqkit/compiler/decomposer/diagonal.py
spinqkit/compiler/decomposer/isometry_decomposer.py
spinqkit/compiler/decomposer/magic_basis_decomposer.py
spinqkit/compiler/decomposer/multi_controlled_gate.py
spinqkit/compiler/decomposer/uniformly_controlled_gate.py
spinqkit/compiler/decomposer/uniformly_controlled_rotation_gate.py
spinqkit/compiler/optimizer/__init__.py
spinqkit/compiler/optimizer/analyze_path.py
spinqkit/compiler/optimizer/cancel_redundant_gates.py
spinqkit/compiler/optimizer/collapse_single_qubit_gates.py
spinqkit/compiler/optimizer/collapse_two_qubit_gates.py
spinqkit/compiler/optimizer/pass_manager.py
spinqkit/compiler/optimizer/quantum_basis_state_optimization.py
spinqkit-0.0.3.dist-info/METADATA
spinqkit-0.0.3.dist-info/WHEEL
spinqkit-0.0.3.dist-info/top_level.txt
spinqkit-0.0.3.dist-info/RECORD
