Metadata-Version: 2.1
Name: spinqkit
Version: 0.0.3
Summary: SpinQ Quantum Software Development Kit
Home-page: UNKNOWN
License: UNKNOWN
Platform: UNKNOWN
Classifier: Development Status :: 5 - Production/Stable
Classifier: Programming Language :: Python :: 3
Classifier: Operating System :: Microsoft :: Windows
Classifier: Operating System :: POSIX :: Linux
Classifier: Operating System :: MacOS
Requires-Python: >=3.8
Requires-Dist: numpy
Requires-Dist: scipy
Requires-Dist: psutil
Requires-Dist: retworkx
Requires-Dist: python-igraph (==0.9.10)
Requires-Dist: pybind11
Requires-Dist: antlr4-python3-runtime (==4.9.2)
Requires-Dist: python-constraint
Requires-Dist: requests
Requires-Dist: matplotlib (>=3.5)
Requires-Dist: pycryptodome (==3.11.0)
